trace_generator/__init__.py
trace_generator/trace_generator.py
trace_generator-2.0.dist-info/LICENSE
trace_generator-2.0.dist-info/METADATA
trace_generator-2.0.dist-info/WHEEL
trace_generator-2.0.dist-info/top_level.txt
trace_generator-2.0.dist-info/RECORD
