Metadata-Version: 2.1
Name: trace_generator
Version: 2.0
Summary: A package for generating random traces based on sequence schemas..
Home-page: https://github.com/alijlidi/trace_generator
Author: Dr. Kovacs Laszlo
Author-email: laszlo.kovacs@uni-miskolc.hu
Classifier: Programming Language :: Python :: 3
Classifier: License :: OSI Approved :: MIT License
Classifier: Operating System :: OS Independent
Requires-Python: >=3.6
License-File: LICENSE
